aws_authenticator/__init__.py
aws_authenticator/aws_config.py
aws_authenticator/cli.py
aws_authenticator/config.py
aws_authenticator/sso.py
aws_authenticator_cli-0.0.5.dist-info/licenses/LICENSE
aws_authenticator_cli-0.0.5.dist-info/METADATA
aws_authenticator_cli-0.0.5.dist-info/WHEEL
aws_authenticator_cli-0.0.5.dist-info/entry_points.txt
aws_authenticator_cli-0.0.5.dist-info/top_level.txt
aws_authenticator_cli-0.0.5.dist-info/RECORD
