Metadata-Version: 2.4
Name: aws-authenticator-cli
Version: 0.0.5
Summary: Simple AWS CLI authenticator using AWS IAM Identity Center (SSO) with credential_process
Author: Kamil Filipek
Requires-Python: >=3.10
License-File: LICENSE
Requires-Dist: boto3>=1.28
Provides-Extra: test
Requires-Dist: pytest>=7.0; extra == "test"
Requires-Dist: pytest-mock>=3.10; extra == "test"
Requires-Dist: pytest-cov>=4.1; extra == "test"
Provides-Extra: lint
Requires-Dist: ruff>=0.6; extra == "lint"
Provides-Extra: typecheck
Requires-Dist: mypy>=1.8; extra == "typecheck"
Provides-Extra: dev
Requires-Dist: pytest>=7.0; extra == "dev"
Requires-Dist: pytest-mock>=3.10; extra == "dev"
Requires-Dist: pytest-cov>=4.1; extra == "dev"
Requires-Dist: ruff>=0.6; extra == "dev"
Requires-Dist: mypy>=1.8; extra == "dev"
Requires-Dist: pre-commit>=3.5; extra == "dev"
Dynamic: license-file
